cutagi.cpython-311-x86_64-linux-gnu.so
pytagi/__init__.py
pytagi/__version.py
pytagi/cuda.py
pytagi/metric.py
pytagi/tagi_utils.py
pytagi/version.txt
pytagi/nn/__init__.py
pytagi/nn/activation.py
pytagi/nn/base_layer.py
pytagi/nn/batch_norm.py
pytagi/nn/conv2d.py
pytagi/nn/convtranspose2d.py
pytagi/nn/data_struct.py
pytagi/nn/ddp.py
pytagi/nn/embedding.py
pytagi/nn/layer_block.py
pytagi/nn/layer_norm.py
pytagi/nn/linear.py
pytagi/nn/lstm.py
pytagi/nn/output_updater.py
pytagi/nn/pooling.py
pytagi/nn/resnet_block.py
pytagi/nn/sequential.py
pytagi/nn/slinear.py
pytagi/nn/slstm.py
pytagi-0.2.1.dist-info/LICENSE
pytagi-0.2.1.dist-info/METADATA
pytagi-0.2.1.dist-info/WHEEL
pytagi-0.2.1.dist-info/top_level.txt
pytagi-0.2.1.dist-info/RECORD
